indicator/__init__.py
indicator/gui.py
indicator/methods.py
indicators_merwan-1.0.0.dist-info/licenses/LICENSE
indicators_merwan-1.0.0.dist-info/METADATA
indicators_merwan-1.0.0.dist-info/WHEEL
indicators_merwan-1.0.0.dist-info/top_level.txt
indicators_merwan-1.0.0.dist-info/RECORD
