Metadata-Version: 2.4
Name: indicators-merwan
Version: 1.0.0
Summary: Simple financial/technical indicators demo package.
Home-page: https://github.com/merwanroudane/indicators
Author: Dr. Merwan Roudane
Author-email: Merwan Roudane <merwanroudane920@gmail.com>
License-Expression: MIT
Classifier: Programming Language :: Python :: 3
Classifier: Programming Language :: Python :: 3 :: Only
Classifier: Operating System :: OS Independent
Requires-Python: >=3.8
License-File: LICENSE
Dynamic: author
Dynamic: home-page
Dynamic: license-file
Dynamic: requires-python
